s2clientprotocol-stubs/METADATA.toml
s2clientprotocol-stubs/build.pyi
s2clientprotocol-stubs/common_pb2.pyi
s2clientprotocol-stubs/data_pb2.pyi
s2clientprotocol-stubs/debug_pb2.pyi
s2clientprotocol-stubs/error_pb2.pyi
s2clientprotocol-stubs/query_pb2.pyi
s2clientprotocol-stubs/raw_pb2.pyi
s2clientprotocol-stubs/sc2api_pb2.pyi
s2clientprotocol-stubs/score_pb2.pyi
s2clientprotocol-stubs/spatial_pb2.pyi
s2clientprotocol-stubs/ui_pb2.pyi
types_s2clientprotocol-5.0.0.20250503.dist-info/licenses/LICENSE
types_s2clientprotocol-5.0.0.20250503.dist-info/METADATA
types_s2clientprotocol-5.0.0.20250503.dist-info/WHEEL
types_s2clientprotocol-5.0.0.20250503.dist-info/top_level.txt
types_s2clientprotocol-5.0.0.20250503.dist-info/RECORD
