Metadata-Version: 2.4
Name: types-s2clientprotocol
Version: 5.0.0.20250503
Summary: Typing stubs for s2clientprotocol
License-Expression: Apache-2.0
Project-URL: Homepage, https://github.com/python/typeshed
Project-URL: GitHub, https://github.com/python/typeshed
Project-URL: Changes, https://github.com/typeshed-internal/stub_uploader/blob/main/data/changelogs/s2clientprotocol.md
Project-URL: Issue tracker, https://github.com/python/typeshed/issues
Project-URL: Chat, https://gitter.im/python/typing
Classifier: Programming Language :: Python :: 3
Classifier: Typing :: Stubs Only
Requires-Python: >=3.9
License-File: LICENSE
Requires-Dist: types-protobuf
Dynamic: license-file
